daf/__init__.py
daf/command_line/__init__.py
daf/command_line/cli_base_utils.py
daf/command_line/experiment/__init__.py
daf/command_line/experiment/bounds.py
daf/command_line/experiment/experiment_configuration.py
daf/command_line/experiment/experiment_utils.py
daf/command_line/experiment/manage_counters.py
daf/command_line/experiment/mode_constraints.py
daf/command_line/experiment/operation_mode.py
daf/command_line/experiment/set_u_ub_matrix.py
daf/command_line/move/__init__.py
daf/command_line/move/ang_move.py
daf/command_line/move/hkl_calc.py
daf/command_line/move/hkl_move.py
daf/command_line/move/move_utils.py
daf/command_line/move/reciprocal_space_map.py
daf/command_line/move/rel_ang_move.py
daf/command_line/query/__init__.py
daf/command_line/query/query_utils.py
daf/command_line/query/sample_position.py
daf/command_line/query/status.py
daf/command_line/query/where.py
daf/command_line/scan/__init__.py
daf/command_line/scan/a1scan.py
daf/command_line/scan/a2scan.py
daf/command_line/scan/a3scan.py
daf/command_line/scan/a4scan.py
daf/command_line/scan/a5scan.py
daf/command_line/scan/a6scan.py
daf/command_line/scan/d1scan.py
daf/command_line/scan/d2scan.py
daf/command_line/scan/d3scan.py
daf/command_line/scan/d4scan.py
daf/command_line/scan/d5scan.py
daf/command_line/scan/d6scan.py
daf/command_line/scan/daf_scan_utils.py
daf/command_line/scan/from_file_scan.py
daf/command_line/scan/hkl_scan.py
daf/command_line/scan/mesh_scan.py
daf/command_line/scan/scan_daf.py
daf/command_line/scan/time_scan.py
daf/command_line/scan/time_scan_daf.py
daf/command_line/support/__init__.py
daf/command_line/support/change_prompt.py
daf/command_line/support/command_help.py
daf/command_line/support/dafmacro.py
daf/command_line/support/gui_all.py
daf/command_line/support/init.py
daf/command_line/support/new_sample.py
daf/command_line/support/reset.py
daf/command_line/support/setup.py
daf/command_line/support/support_utils.py
daf/core/__init__.py
daf/core/main.py
daf/core/matrix_utils.py
dica-0.0.1.dist-info/METADATA
dica-0.0.1.dist-info/WHEEL
dica-0.0.1.dist-info/entry_points.txt
dica-0.0.1.dist-info/top_level.txt
dica-0.0.1.dist-info/RECORD
